celeb_detector/__init__.py
celeb_detector/celeb_prediction_main.py
celeb_detector/celeb_recognition.py
celeb_detector/create_celeb_model.py
celeb_detector-0.0.25.dist-info/LICENSE
celeb_detector-0.0.25.dist-info/METADATA
celeb_detector-0.0.25.dist-info/WHEEL
celeb_detector-0.0.25.dist-info/entry_points.txt
celeb_detector-0.0.25.dist-info/top_level.txt
celeb_detector-0.0.25.dist-info/RECORD
