Metadata-Version: 2.1
Name: celeb-detector
Version: 0.0.25
Summary: Model to recognize celebrities using a face matching algorithm
Home-page: https://github.com/shobhit9618/celeb_recognition
Author: Shobhit Gupta
Author-email: shobhit9618@gmail.com
Classifier: Programming Language :: Python :: 3
Classifier: License :: OSI Approved :: MIT License
Classifier: Operating System :: OS Independent
Requires-Python: >=3.6
License-File: LICENSE
Requires-Dist: annoy
Requires-Dist: face-recognition
Requires-Dist: imutils
Requires-Dist: opencv-python
Requires-Dist: matplotlib
Requires-Dist: numpy
Requires-Dist: tqdm
Requires-Dist: pillow
Requires-Dist: torch
Requires-Dist: onnx2torch
Requires-Dist: requests
